ycsai/__init__.py
ycsai/models/__init__.py
ycsai/models/engines.py
ycsai/models/tasks.py
ycsai/utils/__init__.py
ycsai/utils/download.py
ycsai/utils/experiments.py
ycsai/utils/general.py
ycsai/utils/lion.py
ycsai/utils/loss.py
ycsai/utils/plots.py
ycsai/utils/torch_utils.py
ycsai/utils/val.py
YSCAI-1.0.0.dist-info/METADATA
YSCAI-1.0.0.dist-info/WHEEL
YSCAI-1.0.0.dist-info/top_level.txt
YSCAI-1.0.0.dist-info/RECORD
